examples/__init__.py
examples/ejemplo.py
mauweb/__init__.py
mauweb/app.py
mauweb/request.py
mauweb/response.py
mauweb/router.py
MauWeb-0.0.2.dist-info/LICENSE.md
MauWeb-0.0.2.dist-info/METADATA
MauWeb-0.0.2.dist-info/WHEEL
MauWeb-0.0.2.dist-info/top_level.txt
MauWeb-0.0.2.dist-info/RECORD
