Metadata-Version: 2.1
Name: MauWeb
Version: 0.0.2
Summary: Un pequeño framework para python
Home-page: https://github.com/maubg-debug/mauweb
Author: Maubg
License: UNKNOWN
Platform: UNKNOWN
Classifier: Programming Language :: Python :: 3
Classifier: License :: OSI Approved :: MIT License
Classifier: Operating System :: OS Independent
Requires-Python: >=3.6
